{"run_number": "1732086107387998", "step_name": "users", "task_id": "2", "attempt_id": 0, "name": "_graph_info", "content_type": "gzip+pickle-v2", "type": "metaflow.artifact", "sha": "ef4033c9b72b3b08f61f37de8b378722cc32e015", "ds_type": "local", "location": ":root:/home/hassanmahmood/01-PROFESSIONAL-CAREER/01-ALLIED-BANK-WORKSPACE/MetaFlow-Learning-and-Tutorials/.metaflow", "flow_id": "BasicFlow", "user_name": "hassanmahmood", "tags": [], "system_tags": ["runtime:dev", "metaflow_version:2.12.30", "python_version:3.12.3", "user:hassanmahmood"], "ts_epoch": 1732086108194}