{"run_number": "1732097819933420", "step_name": "compute_payable", "task_id": "6", "attempt_id": 0, "name": "_graph_info", "content_type": "gzip+pickle-v2", "type": "metaflow.artifact", "sha": "b31b2a70de3834b7de35dbe5a759680181f2009f", "ds_type": "local", "location": ":root:/home/hassanmahmood/01-PROFESSIONAL-CAREER/01-ALLIED-BANK-WORKSPACE/MetaFlow-Learning-and-Tutorials/.metaflow", "flow_id": "BasicFlow", "user_name": "hassanmahmood", "tags": [], "system_tags": ["runtime:dev", "python_version:3.12.3", "user:hassanmahmood", "metaflow_version:2.12.30"], "ts_epoch": 1732097822930}